{
  "node": {
    "2dd2b955ee669fe4fdaafe89dbce814e1d5342a8": {
      "workers": {
        "app/page": "(rsc)/./node_modules/next/dist/build/webpack/loaders/next-flight-action-entry-loader.js?actions=%5B%5B%22C%3A%5C%5CUsers%5C%5Cnatta%5C%5COneDrive%5C%5C%E0%B9%80%E0%B8%94%E0%B8%AA%E0%B8%81%E0%B9%8C%E0%B8%97%E0%B9%87%E0%B8%AD%E0%B8%9B%5C%5Cnext%5C%5Cmy-app%5C%5Ccomponents%5C%5CAuthButton.tsx%22%2C%5B%22%24%24ACTION_0%22%5D%5D%5D&__client_imported__=!",
        "app/protected/page": "(rsc)/./node_modules/next/dist/build/webpack/loaders/next-flight-action-entry-loader.js?actions=%5B%5B%22C%3A%5C%5CUsers%5C%5Cnatta%5C%5COneDrive%5C%5C%E0%B9%80%E0%B8%94%E0%B8%AA%E0%B8%81%E0%B9%8C%E0%B8%97%E0%B9%87%E0%B8%AD%E0%B8%9B%5C%5Cnext%5C%5Cmy-app%5C%5Ccomponents%5C%5CAuthButton.tsx%22%2C%5B%22%24%24ACTION_0%22%5D%5D%5D&__client_imported__=!"
      },
      "layer": {
        "app/page": "rsc",
        "app/protected/page": "rsc"
      }
    },
    "2c2b8d247d4b11a47d1493c0fb385ce6f0f27887": {
      "workers": {
        "app/login/page": "(rsc)/./node_modules/next/dist/build/webpack/loaders/next-flight-action-entry-loader.js?actions=%5B%5B%22C%3A%5C%5CUsers%5C%5Cnatta%5C%5COneDrive%5C%5C%E0%B9%80%E0%B8%94%E0%B8%AA%E0%B8%81%E0%B9%8C%E0%B8%97%E0%B9%87%E0%B8%AD%E0%B8%9B%5C%5Cnext%5C%5Cmy-app%5C%5Capp%5C%5Clogin%5C%5Cpage.tsx%22%2C%5B%22%24%24ACTION_0%22%2C%22%24%24ACTION_1%22%5D%5D%5D&__client_imported__=!"
      },
      "layer": {
        "app/login/page": "rsc"
      }
    },
    "bd20c14988fc3a089626d0f71ae740c4d7456ede": {
      "workers": {
        "app/login/page": "(rsc)/./node_modules/next/dist/build/webpack/loaders/next-flight-action-entry-loader.js?actions=%5B%5B%22C%3A%5C%5CUsers%5C%5Cnatta%5C%5COneDrive%5C%5C%E0%B9%80%E0%B8%94%E0%B8%AA%E0%B8%81%E0%B9%8C%E0%B8%97%E0%B9%87%E0%B8%AD%E0%B8%9B%5C%5Cnext%5C%5Cmy-app%5C%5Capp%5C%5Clogin%5C%5Cpage.tsx%22%2C%5B%22%24%24ACTION_0%22%2C%22%24%24ACTION_1%22%5D%5D%5D&__client_imported__=!"
      },
      "layer": {
        "app/login/page": "rsc"
      }
    }
  },
  "edge": {},
  "encryptionKey": "nUIXuZN9WjpZpmC2539CThK90EK93mzpFZw9PN3fbog="
}